[
 {
  "date": "2026-06-14",
  "rhr": 44,
  "hrv": 75,
  "tr": 76,
  "weight": 99.2
 },
 {
  "date": "2026-06-15",
  "rhr": 45,
  "hrv": 68,
  "tr": 79
 },
 {
  "date": "2026-06-16",
  "rhr": 46,
  "hrv": 59,
  "tr": 72
 },
 {
  "date": "2026-06-17",
  "rhr": 47,
  "hrv": 64,
  "tr": 89,
  "weight": 99.0
 },
 {
  "date": "2026-06-18",
  "rhr": 47,
  "hrv": 69,
  "tr": 75
 },
 {
  "date": "2026-06-19",
  "rhr": 50,
  "hrv": 49,
  "tr": 67
 },
 {
  "date": "2026-06-20",
  "rhr": 44,
  "hrv": 65,
  "tr": 78
 },
 {
  "date": "2026-06-21",
  "rhr": 46,
  "tr": 62
 },
 {
  "date": "2026-06-22",
  "rhr": 45,
  "hrv": 75,
  "tr": 47,
  "weight": 98.0
 },
 {
  "date": "2026-06-23",
  "rhr": 48,
  "hrv": 58,
  "tr": 54
 },
 {
  "date": "2026-06-24",
  "rhr": 47,
  "hrv": 62,
  "tr": 54
 },
 {
  "date": "2026-06-25",
  "rhr": 48,
  "hrv": 59,
  "tr": 66
 },
 {
  "date": "2026-06-26",
  "rhr": 45,
  "hrv": 73,
  "tr": 58
 },
 {
  "date": "2026-06-27",
  "rhr": 46,
  "hrv": 68,
  "tr": 55
 },
 {
  "date": "2026-06-28",
  "rhr": 42,
  "hrv": 66,
  "tr": 79
 },
 {
  "date": "2026-06-29",
  "rhr": 42,
  "hrv": 76,
  "tr": 79
 },
 {
  "date": "2026-06-30",
  "rhr": 45,
  "hrv": 64,
  "tr": 92
 },
 {
  "date": "2026-07-01",
  "rhr": 46,
  "hrv": 61,
  "tr": 84
 },
 {
  "date": "2026-07-02",
  "rhr": 46,
  "hrv": 66,
  "tr": 70
 },
 {
  "date": "2026-07-03",
  "rhr": 46,
  "hrv": 63,
  "tr": 59
 },
 {
  "date": "2026-07-04",
  "rhr": 47,
  "hrv": 71,
  "tr": 70
 },
 {
  "date": "2026-07-05",
  "rhr": 46,
  "hrv": 78,
  "tr": 47,
  "weight": 96.2
 },
 {
  "date": "2026-07-06",
  "rhr": 46,
  "hrv": 67,
  "tr": 65
 },
 {
  "date": "2026-07-07",
  "rhr": 46,
  "hrv": 68,
  "tr": 2
 },
 {
  "date": "2026-07-08",
  "rhr": 51,
  "hrv": 53,
  "tr": 1
 },
 {
  "date": "2026-07-09",
  "rhr": 48,
  "hrv": 57,
  "tr": 50
 },
 {
  "date": "2026-07-10",
  "rhr": 47,
  "hrv": 64,
  "tr": 47
 },
 {
  "date": "2026-07-11",
  "rhr": 49,
  "hrv": 54,
  "tr": 53
 },
 {
  "date": "2026-07-12",
  "rhr": 46,
  "hrv": 72,
  "tr": 79
 },
 {
  "date": "2026-07-13",
  "rhr": 45,
  "hrv": 69,
  "tr": 72
 }
]